pymannkendall/__init__.py
pymannkendall/_version.py
pymannkendall/pymannkendall.py
pymannkendall-1.4.3.dist-info/LICENSE.txt
pymannkendall-1.4.3.dist-info/METADATA
pymannkendall-1.4.3.dist-info/WHEEL
pymannkendall-1.4.3.dist-info/top_level.txt
pymannkendall-1.4.3.dist-info/RECORD
