Metadata-Version: 2.1
Name: pymannkendall
Version: 1.4.3
Summary: A python package for non-parametric Mann-Kendall family of trend tests.
Home-page: https://github.com/mmhs013/pymannkendall
Author: Md. Manjurul Hussain Shourov
Author-email: mmhs013@gmail.com
License: MIT
Platform: UNKNOWN
Classifier: Programming Language :: Python :: 2.7
Classifier: Programming Language :: Python :: 3.4
Classifier: Programming Language :: Python :: 3.5
Classifier: Programming Language :: Python :: 3.6
Classifier: Programming Language :: Python :: 3.7
Classifier: Programming Language :: Python :: 3.8
Classifier: Programming Language :: Python :: 3.9
Classifier: License :: OSI Approved :: MIT License
Classifier: Intended Audience :: Science/Research
Classifier: Operating System :: OS Independent
Classifier: Topic :: Scientific/Engineering
Classifier: Development Status :: 5 - Production/Stable
License-File: LICENSE.txt
